pydantic_rpc_cli/__init__.py
pydantic_rpc_cli/cli.py
pydantic_rpc_cli-0.15.1.dist-info/WHEEL
pydantic_rpc_cli-0.15.1.dist-info/entry_points.txt
pydantic_rpc_cli-0.15.1.dist-info/METADATA
pydantic_rpc_cli-0.15.1.dist-info/RECORD
