Metadata-Version: 2.3
Name: pydantic-rpc-cli
Version: 0.15.1
Summary: CLI tool for pydantic-rpc with server runtime support
Author: Yasushi Itoh
Classifier: Programming Language :: Python :: 3.11
Classifier: Programming Language :: Python :: 3.12
Classifier: Programming Language :: Python :: 3.13
Classifier: Programming Language :: Python :: 3.14
Requires-Dist: pydantic-rpc>=0.15.1
Requires-Dist: hypercorn>=0.17.3
Requires-Dist: gunicorn>=20.1.0
Requires-Dist: uvloop>=0.17.0
Requires-Python: >=3.11
